LICENCE.txt
MANIFEST.in
README.rst
setup.py
cmsplugin_porticus/__init__.py
cmsplugin_porticus/cms_plugins.py
cmsplugin_porticus/cms_toolbars.py
cmsplugin_porticus/models.py
cmsplugin_porticus/settings.py
cmsplugin_porticus.egg-info/PKG-INFO
cmsplugin_porticus.egg-info/SOURCES.txt
cmsplugin_porticus.egg-info/dependency_links.txt
cmsplugin_porticus.egg-info/not-zip-safe
cmsplugin_porticus.egg-info/requires.txt
cmsplugin_porticus.egg-info/top_level.txt
cmsplugin_porticus/migrations/0001_initial.py
cmsplugin_porticus/migrations/0002_add_limits.py
cmsplugin_porticus/migrations/0003_add_cloudtag.py
cmsplugin_porticus/migrations/__init__.py
cmsplugin_porticus/south_migrations/0001_initial.py
cmsplugin_porticus/south_migrations/0002_auto__chg_field_galleryplugin_gallery.py
cmsplugin_porticus/south_migrations/__init__.py
cmsplugin_porticus/templates/porticus/cms/album_detail.html
cmsplugin_porticus/templates/porticus/cms/gallery_detail.html