Metadata-Version: 1.1
Name: cmsplugin-porticus
Version: 0.6.0
Summary: 
